{
  "date": "2026-04-19",
  "games": [
    {
      "home_team": "New York Yankees",
      "away_team": "Kansas City Royals",
      "commence_time": "7:05 PM ET",
      "pick": "New York Yankees",
      "pick_odds": -115,
      "ev": 64.61521739130434,
      "kelly": 25,
      "sim_home_win_pct": 88.05,
      "sim_away_win_pct": 6.29
    },
    {
      "home_team": "Boston Red Sox",
      "away_team": "Detroit Tigers",
      "commence_time": "2026-04-19T20:35:00Z",
      "pick": "Detroit Tigers",
      "pick_odds": -4000,
      "ev": -14.750750000000012,
      "kelly": 0,
      "sim_home_win_pct": 9.56,
      "sim_away_win_pct": 83.17
    },
    {
      "home_team": "Philadelphia Phillies",
      "away_team": "Atlanta Braves",
      "commence_time": "7:05 PM ET",
      "pick": "Atlanta Braves",
      "pick_odds": -112,
      "ev": 47.907857142857125,
      "kelly": 25,
      "sim_home_win_pct": 12.22,
      "sim_away_win_pct": 78.14
    },
    {
      "home_team": "Arizona Diamondbacks",
      "away_team": "Toronto Blue Jays",
      "commence_time": "9:40 PM ET",
      "pick": "Toronto Blue Jays",
      "pick_odds": 105,
      "ev": 36.65299999999998,
      "kelly": 25,
      "sim_home_win_pct": 21.78,
      "sim_away_win_pct": 66.66
    },
    {
      "home_team": "Seattle Mariners",
      "away_team": "Texas Rangers",
      "commence_time": "2026-04-19T20:10:00Z",
      "pick": "Seattle Mariners",
      "pick_odds": -3000,
      "ev": -40.06666666666666,
      "kelly": 0,
      "sim_home_win_pct": 58,
      "sim_away_win_pct": 26.39
    },
    {
      "home_team": "Los Angeles Angels",
      "away_team": "San Diego Padres",
      "commence_time": "10:07 PM ET",
      "pick": "Los Angeles Angels",
      "pick_odds": 400,
      "ev": 118.6,
      "kelly": 25,
      "sim_home_win_pct": 43.72,
      "sim_away_win_pct": 39.78
    },
    {
      "home_team": "Athletics",
      "away_team": "Chicago White Sox",
      "commence_time": "9:40 PM ET",
      "pick": "Athletics",
      "pick_odds": 1400,
      "ev": 685.7000000000002,
      "kelly": 25,
      "sim_home_win_pct": 52.38,
      "sim_away_win_pct": 33.16
    }
  ],
  "sent_at": [
    "2026-04-19T16:28:57.330Z",
    "2026-04-19T19:44:25.204Z",
    "2026-04-19T22:39:35.534Z"
  ]
}